fast_csv/__init__.py
fast_csv/fast_csv.py
fast_csv-1.3.4.dist-info/METADATA
fast_csv-1.3.4.dist-info/WHEEL
fast_csv-1.3.4.dist-info/entry_points.txt
fast_csv-1.3.4.dist-info/top_level.txt
fast_csv-1.3.4.dist-info/RECORD
