Metadata-Version: 2.1
Name: fast-csv
Version: 1.3.4
Summary: reduce memory usage
Home-page: https://github.com/YUX-IO/fast_csv
Author: yux
Author-email: yu.xiao.fr@gmail.com
License: MIT
Platform: UNKNOWN
Requires-Dist: numpy
Requires-Dist: pandas
